semmatch/__init__.py
semmatch/__main__.py
semmatch/autodoc.py
semmatch/core.py
semmatch/groups.py
semmatch/gui.py
semmatch/image.py
tests/__init__.py
tests/test_templateMatch.py
semmatch-0.0.16.dist-info/LICENSE.txt
semmatch-0.0.16.dist-info/METADATA
semmatch-0.0.16.dist-info/WHEEL
semmatch-0.0.16.dist-info/entry_points.txt
semmatch-0.0.16.dist-info/top_level.txt
semmatch-0.0.16.dist-info/RECORD
