Metadata-Version: 2.1
Name: semmatch
Version: 0.0.16
Summary: template matching tool for SerialEM
Home-page: UNKNOWN
Author: Albert Xu
Author-email: albert.t.xu@gmail.com
License: UNKNOWN
Platform: UNKNOWN
Classifier: Programming Language :: Python :: 3
Classifier: License :: OSI Approved :: MIT License
Classifier: Operating System :: OS Independent
Requires-Dist: imageio
Requires-Dist: numpy
Requires-Dist: opencv-python
Requires-Dist: PyQt5
Requires-Dist: Pillow
Requires-Dist: scikit-image
Requires-Dist: scikit-learn
Requires-Dist: scipy
